LICENSE.txt
README.md
setup.cfg
setup.py
emailSpoofDetection/__init__.py
emailSpoofDetection/emailSpoofDetection.py
emailSpoofDetection.egg-info/PKG-INFO
emailSpoofDetection.egg-info/SOURCES.txt
emailSpoofDetection.egg-info/dependency_links.txt
emailSpoofDetection.egg-info/top_level.txt