Metadata-Version: 2.1
Name: emailSpoofDetection
Version: 1.0.0
Summary: To identify and prevent email spoofing attacks
Home-page: https://github.com/govindasamyarun/emailSpoofDetection.git
Author: Arun Govindasamy
Keywords: security,spoof,email parser,email header analysis
License-File: LICENSE.txt
